setup.py
shelly
shelly.egg-info/PKG-INFO
shelly.egg-info/SOURCES.txt
shelly.egg-info/dependency_links.txt
shelly.egg-info/requires.txt
shelly.egg-info/top_level.txt
shelly_cmd/__init__.py
shelly_cmd/drop.py
shelly_cmd/exists.py
shelly_cmd/groupby.py
shelly_cmd/highlight.py
shelly_cmd/join.py
shelly_cmd/max.py
shelly_cmd/min.py
shelly_cmd/range.py
shelly_cmd/repeat.py
shelly_cmd/shrandom.py
shelly_cmd/space.py
shelly_cmd/subsample.py
shelly_cmd/take.py
shelly_cmd/trickle.py