Metadata-Version: 1.0
Name: shelly
Version: 0.2.1
Summary: Standalone tools to make the shell better.
Home-page: http://bitbucket.org/larsyencken/shelly/
Author: Lars Yencken
Author-email: lars@yencken.org
License: BSD
Platform: UNKNOWN
